harmony_hpack/PackFile.py
harmony_hpack/__init__.py
harmony_hpack/config.py
harmony_hpack/hdc.py
harmony_hpack/main.py
harmony_hpack/packSign.py
harmony_hpack/sign.py
harmony_hpack/signInfo.py
harmony_hpack/template.py
harmony_hpack/toolConfig.py
harmony_hpack/utils.py
harmony_hpack/version.py
harmony_hpack/__pycache__/__init__.cpython-313.pyc
harmony_hpack/__pycache__/config.cpython-313.pyc
harmony_hpack/__pycache__/pack_sign.cpython-313.pyc
harmony_hpack/__pycache__/sign_uploader.cpython-313.pyc
harmony_hpack/__pycache__/template_config.cpython-313.pyc
harmony_hpack/__pycache__/toolConfig.cpython-313.pyc
harmony_hpack/__pycache__/utils.cpython-313.pyc
harmony_hpack/__pycache__/version.cpython-313.pyc
harmony_hpack/hap-manifest-sign-tool/hap-sign-tool.jar
harmony_hpack/hap-manifest-sign-tool/manifest-sign-tool-1.0.0.jar
harmony_hpack/hap-manifest-sign-tool/lib/bcprov-jdk18on-1.75.jar
harmony_hpack/hap-manifest-sign-tool/lib/commons-codec-1.15.jar
harmony_hpack/hap-manifest-sign-tool/lib/gson-2.9.1.jar
harmony_hpack/hap-manifest-sign-tool/lib/log4j-api-2.23.1.jar
harmony_hpack/hap-manifest-sign-tool/lib/log4j-core-2.23.1.jar
harmony_hpack/hap-manifest-sign-tool/lib/lombok-1.18.26.jar
harmony_hpack/sign/harmony.p12
harmony_hpack/sign/release.cer
harmony_hpack/sign/test_release.p7b
harmony_hpack/templates/cartoon.html
harmony_hpack/templates/default.html
harmony_hpack/templates/simple.html
harmony_hpack/templates/tech.html
harmony_hpack/templates/tradition.html
harmony_hpack-1.0.9.dist-info/METADATA
harmony_hpack-1.0.9.dist-info/WHEEL
harmony_hpack-1.0.9.dist-info/entry_points.txt
harmony_hpack-1.0.9.dist-info/top_level.txt
harmony_hpack-1.0.9.dist-info/RECORD
