Metadata-Version: 2.4
Name: harmony-hpack
Version: 1.0.9
Requires-Python: >=3.7
Requires-Dist: json5
Requires-Dist: segno
Requires-Dist: prompt_toolkit
Dynamic: description
Dynamic: description-content-type
Dynamic: requires-dist
Dynamic: requires-python
